pushing_outshoot_unfold/__init__.py
pushing_outshoot_unfold/__main__.py
pushing_outshoot_unfold/ascii.py
pushing_outshoot_unfold/banner.py
pushing_outshoot_unfold/eng.py
pushing_outshoot_unfold/interactions.py
pushing_outshoot_unfold/math.py
pushing_outshoot_unfold/sci.py
pushing_outshoot_unfold/sound.py
pushing_outshoot_unfold/days/000a.toml
pushing_outshoot_unfold/days/001a.toml
pushing_outshoot_unfold/days/001b.toml
pushing_outshoot_unfold/days/002a.toml
pushing_outshoot_unfold/days/002b.toml
pushing_outshoot_unfold/days/003a.toml
pushing_outshoot_unfold/days/003b.toml
pushing_outshoot_unfold/days/004a.toml
pushing_outshoot_unfold/days/004b.toml
pushing_outshoot_unfold/days/005a.toml
pushing_outshoot_unfold/days/005b.toml
pushing_outshoot_unfold/days/006a.toml
pushing_outshoot_unfold/days/006b.toml
pushing_outshoot_unfold/days/007a.toml
pushing_outshoot_unfold/days/007b.toml
pushing_outshoot_unfold/days/008a.toml
pushing_outshoot_unfold/days/008b.toml
pushing_outshoot_unfold/days/009a.toml
pushing_outshoot_unfold/days/009b.toml
pushing_outshoot_unfold/days/010a.toml
pushing_outshoot_unfold/days/010b.toml
pushing_outshoot_unfold/days/011a.toml
pushing_outshoot_unfold/days/011b.toml
pushing_outshoot_unfold/days/012a.toml
pushing_outshoot_unfold/days/012b.toml
pushing_outshoot_unfold/days/013a.toml
pushing_outshoot_unfold/days/013b.toml
pushing_outshoot_unfold/days/014a.toml
pushing_outshoot_unfold/days/014b.toml
pushing_outshoot_unfold/days/015a.toml
pushing_outshoot_unfold/days/015b.toml
pushing_outshoot_unfold/days/016a.toml
pushing_outshoot_unfold/days/016b.toml
pushing_outshoot_unfold/days/017a.toml
pushing_outshoot_unfold/days/017b.toml
pushing_outshoot_unfold/days/018a.toml
pushing_outshoot_unfold/days/018b.toml
pushing_outshoot_unfold/days/019a.toml
pushing_outshoot_unfold/days/019b.toml
pushing_outshoot_unfold/days/020a.toml
pushing_outshoot_unfold/days/020b.toml
pushing_outshoot_unfold/days/021a.toml
pushing_outshoot_unfold/days/021b.toml
pushing_outshoot_unfold-3.0.0.dist-info/LICENSE
pushing_outshoot_unfold-3.0.0.dist-info/METADATA
pushing_outshoot_unfold-3.0.0.dist-info/WHEEL
pushing_outshoot_unfold-3.0.0.dist-info/entry_points.txt
pushing_outshoot_unfold-3.0.0.dist-info/top_level.txt
pushing_outshoot_unfold-3.0.0.dist-info/RECORD
