Metadata-Version: 2.1
Name: pushing-outshoot-unfold
Version: 3.0.0
Summary: A game about a teen getting through quarantine in Covid.
Home-page: https://github.com/po-unfold
Author: Cole, Harshini, Cassidy
Author-email: po-unfold@colewilson.xyz
License: none
Platform: UNKNOWN
Classifier: Programming Language :: Python :: 3
Requires-Python: >=3.6
Requires-Dist: blessed
Requires-Dist: toml
Requires-Dist: replit
